datacite/__init__.py
datacite/client.py
datacite/errors.py
datacite/jsonutils.py
datacite/request.py
datacite/rest_client.py
datacite/schema40.py
datacite/schema41.py
datacite/schema42.py
datacite/schema43.py
datacite/schema45.py
datacite/xmlutils.py
datacite/schemas/datacite-v4.0.json
datacite/schemas/datacite-v4.1.json
datacite/schemas/datacite-v4.2.json
datacite/schemas/datacite-v4.3.json
datacite/schemas/datacite-v4.5.json
datacite/schemas/ietf-bcp-47.json
datacite/schemas/iso-8601.json
datacite-1.3.1.dist-info/LICENSE
datacite-1.3.1.dist-info/METADATA
datacite-1.3.1.dist-info/WHEEL
datacite-1.3.1.dist-info/top_level.txt
datacite-1.3.1.dist-info/RECORD
