Metadata-Version: 2.1
Name: datacite
Version: 1.3.1
Summary: "A Python client for DataCite MDS and REST APIs."
Home-page: https://github.com/inveniosoftware/datacite
Author: Invenio Collaboration
Author-email: info@inveniosoftware.org
License: BSD
Keywords: datacite doi
Platform: UNKNOWN
Classifier: Programming Language :: Python :: 3
Classifier: Development Status :: 5 - Production/Stable
Classifier: Intended Audience :: Developers
Classifier: License :: OSI Approved :: BSD License
Classifier: Operating System :: OS Independent
Classifier: Topic :: Utilities
Requires-Python: >=3.9
License-File: LICENSE
Requires-Dist: jsonschema>=3.0.0
Requires-Dist: lxml>=4.5.2
Requires-Dist: requests>=2.12.2
Requires-Dist: idutils>=1.0.0
Requires-Dist: importlib-metadata>=6.11.0
Provides-Extra: all
Requires-Dist: datacite[tests]; extra == "all"
Provides-Extra: docs
Requires-Dist: Sphinx>=4.5.0; extra == "docs"
Provides-Extra: tests
Requires-Dist: responses>=0.10.6; extra == "tests"
Requires-Dist: mock>=1.3.0; extra == "tests"
Requires-Dist: pytest-invenio>=1.4.0; extra == "tests"
Requires-Dist: pytest-black-ng>=0.4.0; extra == "tests"
Requires-Dist: datacite[docs]; extra == "tests"
